fusets/__init__.py
fusets/_phenolopy.py
fusets/_xarray_utils.py
fusets/analytics.py
fusets/base.py
fusets/ccdc.py
fusets/mogpr.py
fusets/peakvalley.py
fusets/whittaker.py
fusets/cropsar/__init__.py
fusets/openeo/__init__.py
fusets/openeo/mogpr_udf.py
fusets/openeo/peakvalley_udf.py
fusets/openeo/phenology_udf.py
fusets/openeo/whittaker_udf.py
fusets/openeo/services/__init__.py
fusets/openeo/services/helpers.py
fusets/openeo/services/publish_mogpr.py
fusets/openeo/services/publish_peakvalley.py
fusets/openeo/services/publish_phenology.py
fusets/openeo/services/publish_whittaker.py
fusets-2.0.1.dist-info/LICENSE
fusets-2.0.1.dist-info/METADATA
fusets-2.0.1.dist-info/WHEEL
fusets-2.0.1.dist-info/top_level.txt
fusets-2.0.1.dist-info/RECORD
